prefect_huaweicloud/__init__.py
prefect_huaweicloud/obs_block.py
prefect_hwc-0.2.0.dist-info/METADATA
prefect_hwc-0.2.0.dist-info/WHEEL
prefect_hwc-0.2.0.dist-info/top_level.txt
prefect_hwc-0.2.0.dist-info/RECORD
