Metadata-Version: 2.1
Name: prefect-hwc
Version: 0.2.0
Summary: Prefect collection of tasks and sub flows to integrate with HuaweiCloud
Home-page: https://gitee.com/HuaweiCloudDeveloper/huaweicloud-prefect-block-python
Author: HuaweiCloud
Author-email: 
License: Apache License 2.0
Keywords: prefect
Requires-Python: >=3.9
Requires-Dist: pydantic ==1.10.11
Requires-Dist: esdk-obs-python
Requires-Dist: prefect >=2.10.11
